yemot_api/__init__.py
yemot_api/_yemot_api_base.py
yemot_api/api_model.py
yemot_api/api_response.py
yemot_api/async_yemot_api.py
yemot_api/const.py
yemot_api/exceptions.py
yemot_api/input_types.py
yemot_api/types.py
yemot_api/utils.py
yemot_api/yemot_api.py
yemot_api-0.1.13.dist-info/METADATA
yemot_api-0.1.13.dist-info/WHEEL
yemot_api-0.1.13.dist-info/entry_points.txt
yemot_api-0.1.13.dist-info/licenses/LICENSE
yemot_api-0.1.13.dist-info/RECORD
