Metadata-Version: 2.4
Name: yemot-api
Version: 0.1.13
Summary: python client for yemot api module and yemot rest api
Project-URL: Homepage, https://github.com/zevisvei/yemot_api
Project-URL: Issues, https://github.com/zevisvei/yemot_api/issues
Author-email: zevisvei <zszszszs491@gmail.com>
License: GPL-3.0-or-later
License-File: LICENSE
Classifier: License :: OSI Approved :: GNU General Public License v3 (GPLv3)
Requires-Python: >=3.11
Requires-Dist: httpx>=0.28.1
Requires-Dist: pydantic>=2.12.3
Requires-Dist: requests>=2.32.5
